MANIFEST.in
README.md
setup.py
decay/__init__.py
decay/comms.py
decay/context.py
decay/feedback.py
decay/main.py
decay/reports.py
decay/test_main.py
decay/util.py
decay/analyzers/__init__.py
decay/analyzers/confluence.py
decay/analyzers/github.py
decay/markers/__init__.py
decay/markers/confluence.py
decay/markers/github.py
docdecay.egg-info/PKG-INFO
docdecay.egg-info/SOURCES.txt
docdecay.egg-info/dependency_links.txt
docdecay.egg-info/entry_points.txt
docdecay.egg-info/requires.txt
docdecay.egg-info/top_level.txt
docs/tooth-64.png
docs/tooth.png