Metadata-Version: 2.1
Name: docdecay
Version: 0.2.5
Summary: Monitor documentation for staleness
Home-page: https://github.com/kshehadeh/decay
Author: Karim Shehadeh
Author-email: kshehadeh@underarmour.com
License: MIT
Platform: UNKNOWN
Classifier: License :: OSI Approved :: MIT License
Classifier: Programming Language :: Python :: 3
Classifier: Programming Language :: Python :: 3.7
